[{"HORA":"16:20","PONTO":"TERMINAL CABRAL","DIA":"1","NUM":"104406","TABELA":"4-2","ADAPT":"ELEVADOR","COD":"X42"},{"HORA":"16:58","PONTO":"TERMINAL CAPAO DA IMBUIA","DIA":"1","NUM":"104703","TABELA":"4-2","ADAPT":"ELEVADOR","COD":"X42"},{"HORA":"17:33","PONTO":"TERMINAL CABRAL","DIA":"1","NUM":"104406","TABELA":"4-2","ADAPT":"ELEVADOR","COD":"X42"},{"HORA":"18:13","PONTO":"TERMINAL CAPAO DA IMBUIA","DIA":"1","NUM":"104703","TABELA":"4-2","ADAPT":"ELEVADOR","COD":"X42"},{"HORA":"18:48","PONTO":"TERMINAL CABRAL","DIA":"1","NUM":"104406","TABELA":"4-2","ADAPT":"ELEVADOR","COD":"X42"},{"HORA":"19:27","PONTO":"TERMINAL CAPAO DA IMBUIA","DIA":"1","NUM":"104703","TABELA":"4-2","ADAPT":"ELEVADOR","COD":"X42"},{"HORA":"19:57","PONTO":"TERMINAL CABRAL","DIA":"1","NUM":"104406","TABELA":"4-2","ADAPT":"ELEVADOR","COD":"X42"},{"HORA":"20:24","PONTO":"TERMINAL CAPAO DA IMBUIA","DIA":"1","NUM":"104703","TABELA":"4-2","ADAPT":"ELEVADOR","COD":"X42"},{"HORA":"20:49","PONTO":"TERMINAL CABRAL","DIA":"1","NUM":"104406","TABELA":"4-2","ADAPT":"ELEVADOR","COD":"X42"},{"HORA":"21:17","PONTO":"TERMINAL CAPAO DA IMBUIA","DIA":"1","NUM":"104703","TABELA":"4-2","ADAPT":"ELEVADOR","COD":"X42"},{"HORA":"21:42","PONTO":"TERMINAL CABRAL","DIA":"1","NUM":"104406","TABELA":"4-2","ADAPT":"ELEVADOR","COD":"X42"},{"HORA":"22:10","PONTO":"TERMINAL CAPAO DA IMBUIA","DIA":"1","NUM":"104703","TABELA":"4-2","ADAPT":"ELEVADOR","COD":"X42"},{"HORA":"22:35","PONTO":"TERMINAL CABRAL","DIA":"1","NUM":"104406","TABELA":"4-2","ADAPT":"ELEVADOR","COD":"X42"},{"HORA":"23:03","PONTO":"TERMINAL CAPAO DA IMBUIA","DIA":"1","NUM":"104703","TABELA":"4-2","ADAPT":"ELEVADOR","COD":"X42"},{"HORA":"23:28","PONTO":"TERMINAL CABRAL","DIA":"1","NUM":"104406","TABELA":"4-2","ADAPT":"ELEVADOR","COD":"X42"},{"HORA":"23:54","PONTO":"TERMINAL CAPAO DA IMBUIA","DIA":"1","NUM":"104703","TABELA":"4-2","ADAPT":"ELEVADOR","COD":"X42"},{"HORA":"00:16","PONTO":"TERMINAL CABRAL","DIA":"1","NUM":"104406","TABELA":"4-2","ADAPT":"ELEVADOR","COD":"X42"}]