[{"HORA":"06:00","PONTO":"TERMINAL CABRAL","DIA":"2","NUM":"109085","TABELA":"2","ADAPT":"RAMPA ELÉTRICA","COD":"700"},{"HORA":"06:15","PONTO":"E.T.CIRC.MILITAR SENT.PINHEIR.","DIA":"2","NUM":"109019","TABELA":"2","ADAPT":"RAMPA ELÉTRICA","COD":"700"},{"HORA":"06:45","PONTO":"TERMINAL PINHEIRINHO","DIA":"2","NUM":"105706","TABELA":"2","ADAPT":"RAMPA ELÉTRICA","COD":"700"},{"HORA":"07:15","PONTO":"E.T. CIRCULO MILITAR / CABRAL","DIA":"2","NUM":"109017","TABELA":"2","ADAPT":"RAMPA ELÉTRICA","COD":"700"},{"HORA":"07:30","PONTO":"TERMINAL CABRAL","DIA":"2","NUM":"109085","TABELA":"2","ADAPT":"RAMPA ELÉTRICA","COD":"700"},{"HORA":"07:45","PONTO":"E.T.CIRC.MILITAR SENT.PINHEIR.","DIA":"2","NUM":"109019","TABELA":"2","ADAPT":"RAMPA ELÉTRICA","COD":"700"},{"HORA":"08:15","PONTO":"TERMINAL PINHEIRINHO","DIA":"2","NUM":"105706","TABELA":"2","ADAPT":"RAMPA ELÉTRICA","COD":"700"},{"HORA":"08:45","PONTO":"E.T. CIRCULO MILITAR / CABRAL","DIA":"2","NUM":"109017","TABELA":"2","ADAPT":"RAMPA ELÉTRICA","COD":"700"},{"HORA":"09:00","PONTO":"TERMINAL CABRAL","DIA":"2","NUM":"109085","TABELA":"2","ADAPT":"RAMPA ELÉTRICA","COD":"700"},{"HORA":"09:15","PONTO":"E.T.CIRC.MILITAR SENT.PINHEIR.","DIA":"2","NUM":"109019","TABELA":"2","ADAPT":"RAMPA ELÉTRICA","COD":"700"},{"HORA":"09:45","PONTO":"TERMINAL PINHEIRINHO","DIA":"2","NUM":"105706","TABELA":"2","ADAPT":"RAMPA ELÉTRICA","COD":"700"},{"HORA":"10:15","PONTO":"E.T. CIRCULO MILITAR / CABRAL","DIA":"2","NUM":"109017","TABELA":"2","ADAPT":"RAMPA ELÉTRICA","COD":"700"},{"HORA":"10:30","PONTO":"TERMINAL CABRAL","DIA":"2","NUM":"109085","TABELA":"2","ADAPT":"RAMPA ELÉTRICA","COD":"700"},{"HORA":"10:45","PONTO":"E.T.CIRC.MILITAR SENT.PINHEIR.","DIA":"2","NUM":"109019","TABELA":"2","ADAPT":"RAMPA ELÉTRICA","COD":"700"},{"HORA":"11:15","PONTO":"TERMINAL PINHEIRINHO","DIA":"2","NUM":"105706","TABELA":"2","ADAPT":"RAMPA ELÉTRICA","COD":"700"},{"HORA":"11:45","PONTO":"E.T. CIRCULO MILITAR / CABRAL","DIA":"2","NUM":"109017","TABELA":"2","ADAPT":"RAMPA ELÉTRICA","COD":"700"},{"HORA":"12:00","PONTO":"TERMINAL CABRAL","DIA":"2","NUM":"109085","TABELA":"2","ADAPT":"RAMPA ELÉTRICA","COD":"700"},{"HORA":"12:15","PONTO":"E.T.CIRC.MILITAR SENT.PINHEIR.","DIA":"2","NUM":"109019","TABELA":"2","ADAPT":"RAMPA ELÉTRICA","COD":"700"},{"HORA":"12:45","PONTO":"TERMINAL PINHEIRINHO","DIA":"2","NUM":"105706","TABELA":"2","ADAPT":"RAMPA ELÉTRICA","COD":"700"},{"HORA":"13:15","PONTO":"E.T. CIRCULO MILITAR / CABRAL","DIA":"2","NUM":"109017","TABELA":"2","ADAPT":"RAMPA ELÉTRICA","COD":"700"},{"HORA":"13:31","PONTO":"TERMINAL CABRAL","DIA":"2","NUM":"109085","TABELA":"2","ADAPT":"RAMPA ELÉTRICA","COD":"700"},{"HORA":"13:47","PONTO":"E.T.CIRC.MILITAR SENT.PINHEIR.","DIA":"2","NUM":"109019","TABELA":"2","ADAPT":"RAMPA ELÉTRICA","COD":"700"},{"HORA":"14:20","PONTO":"TERMINAL PINHEIRINHO","DIA":"2","NUM":"105706","TABELA":"2","ADAPT":"RAMPA ELÉTRICA","COD":"700"},{"HORA":"14:53","PONTO":"E.T. CIRCULO MILITAR / CABRAL","DIA":"2","NUM":"109017","TABELA":"2","ADAPT":"RAMPA ELÉTRICA","COD":"700"},{"HORA":"15:09","PONTO":"TERMINAL CABRAL","DIA":"2","NUM":"109085","TABELA":"2","ADAPT":"RAMPA ELÉTRICA","COD":"700"},{"HORA":"15:23","PONTO":"E.T.CIRC.MILITAR SENT.PINHEIR.","DIA":"2","NUM":"109019","TABELA":"2","ADAPT":"RAMPA ELÉTRICA","COD":"700"},{"HORA":"15:53","PONTO":"TERMINAL PINHEIRINHO","DIA":"2","NUM":"105706","TABELA":"2","ADAPT":"RAMPA ELÉTRICA","COD":"700"},{"HORA":"16:22","PONTO":"E.T. CIRCULO MILITAR / CABRAL","DIA":"2","NUM":"109017","TABELA":"2","ADAPT":"RAMPA ELÉTRICA","COD":"700"},{"HORA":"16:37","PONTO":"TERMINAL CABRAL","DIA":"2","NUM":"109085","TABELA":"2","ADAPT":"RAMPA ELÉTRICA","COD":"700"},{"HORA":"16:52","PONTO":"E.T.CIRC.MILITAR SENT.PINHEIR.","DIA":"2","NUM":"109019","TABELA":"2","ADAPT":"RAMPA ELÉTRICA","COD":"700"},{"HORA":"17:22","PONTO":"TERMINAL PINHEIRINHO","DIA":"2","NUM":"105706","TABELA":"2","ADAPT":"RAMPA ELÉTRICA","COD":"700"},{"HORA":"17:53","PONTO":"E.T. CIRCULO MILITAR / CABRAL","DIA":"2","NUM":"109017","TABELA":"2","ADAPT":"RAMPA ELÉTRICA","COD":"700"},{"HORA":"18:08","PONTO":"TERMINAL CABRAL","DIA":"2","NUM":"109085","TABELA":"2","ADAPT":"RAMPA ELÉTRICA","COD":"700"},{"HORA":"18:23","PONTO":"E.T.CIRC.MILITAR SENT.PINHEIR.","DIA":"2","NUM":"109019","TABELA":"2","ADAPT":"RAMPA ELÉTRICA","COD":"700"},{"HORA":"18:55","PONTO":"TERMINAL PINHEIRINHO","DIA":"2","NUM":"105706","TABELA":"2","ADAPT":"RAMPA ELÉTRICA","COD":"700"},{"HORA":"19:27","PONTO":"E.T. CIRCULO MILITAR / CABRAL","DIA":"2","NUM":"109017","TABELA":"2","ADAPT":"RAMPA ELÉTRICA","COD":"700"},{"HORA":"19:42","PONTO":"TERMINAL CABRAL","DIA":"2","NUM":"109085","TABELA":"2","ADAPT":"RAMPA ELÉTRICA","COD":"700"},{"HORA":"19:57","PONTO":"E.T.CIRC.MILITAR SENT.PINHEIR.","DIA":"2","NUM":"109019","TABELA":"2","ADAPT":"RAMPA ELÉTRICA","COD":"700"},{"HORA":"20:27","PONTO":"TERMINAL PINHEIRINHO","DIA":"2","NUM":"105706","TABELA":"2","ADAPT":"RAMPA ELÉTRICA","COD":"700"},{"HORA":"20:57","PONTO":"E.T. CIRCULO MILITAR / CABRAL","DIA":"2","NUM":"109017","TABELA":"2","ADAPT":"RAMPA ELÉTRICA","COD":"700"},{"HORA":"21:12","PONTO":"TERMINAL CABRAL","DIA":"2","NUM":"109085","TABELA":"2","ADAPT":"RAMPA ELÉTRICA","COD":"700"},{"HORA":"21:27","PONTO":"E.T.CIRC.MILITAR SENT.PINHEIR.","DIA":"2","NUM":"109019","TABELA":"2","ADAPT":"RAMPA ELÉTRICA","COD":"700"},{"HORA":"21:57","PONTO":"TERMINAL PINHEIRINHO","DIA":"2","NUM":"105706","TABELA":"2","ADAPT":"RAMPA ELÉTRICA","COD":"700"},{"HORA":"22:27","PONTO":"E.T. CIRCULO MILITAR / CABRAL","DIA":"2","NUM":"109017","TABELA":"2","ADAPT":"RAMPA ELÉTRICA","COD":"700"},{"HORA":"22:43","PONTO":"TERMINAL CABRAL","DIA":"2","NUM":"109085","TABELA":"2","ADAPT":"RAMPA ELÉTRICA","COD":"700"},{"HORA":"22:59","PONTO":"E.T.CIRC.MILITAR SENT.PINHEIR.","DIA":"2","NUM":"109019","TABELA":"2","ADAPT":"RAMPA ELÉTRICA","COD":"700"},{"HORA":"23:30","PONTO":"TERMINAL PINHEIRINHO","DIA":"2","NUM":"105706","TABELA":"2","ADAPT":"RAMPA ELÉTRICA","COD":"700"},{"HORA":"00:00","PONTO":"E.T. CIRCULO MILITAR / CABRAL","DIA":"2","NUM":"109017","TABELA":"2","ADAPT":"RAMPA ELÉTRICA","COD":"700"}]