[{"HORA":"06:02","PONTO":"TERMINAL BAIRRO ALTO","DIA":"2","NUM":"109120","TABELA":"3","ADAPT":"RAMPA ELÉTRICA","COD":"307"},{"HORA":"06:27","PONTO":"TUBO NESTOR DE CASTRO","DIA":"2","NUM":"109055","TABELA":"3","ADAPT":"RAMPA ELÉTRICA","COD":"307"},{"HORA":"06:44","PONTO":"TERMINAL SANTA FELICIDADE","DIA":"2","NUM":"109121","TABELA":"3","ADAPT":"RAMPA ELÉTRICA","COD":"307"},{"HORA":"07:04","PONTO":"TUBO TIRADENTES","DIA":"2","NUM":"109053","TABELA":"3","ADAPT":"RAMPA ELÉTRICA","COD":"307"},{"HORA":"07:31","PONTO":"TERMINAL BAIRRO ALTO","DIA":"2","NUM":"109120","TABELA":"3","ADAPT":"RAMPA ELÉTRICA","COD":"307"},{"HORA":"07:57","PONTO":"TUBO NESTOR DE CASTRO","DIA":"2","NUM":"109055","TABELA":"3","ADAPT":"RAMPA ELÉTRICA","COD":"307"},{"HORA":"08:17","PONTO":"TERMINAL SANTA FELICIDADE","DIA":"2","NUM":"109121","TABELA":"3","ADAPT":"RAMPA ELÉTRICA","COD":"307"},{"HORA":"08:38","PONTO":"TUBO TIRADENTES","DIA":"2","NUM":"109053","TABELA":"3","ADAPT":"RAMPA ELÉTRICA","COD":"307"},{"HORA":"09:06","PONTO":"TERMINAL BAIRRO ALTO","DIA":"2","NUM":"109120","TABELA":"3","ADAPT":"RAMPA ELÉTRICA","COD":"307"},{"HORA":"09:34","PONTO":"TUBO NESTOR DE CASTRO","DIA":"2","NUM":"109055","TABELA":"3","ADAPT":"RAMPA ELÉTRICA","COD":"307"},{"HORA":"09:55","PONTO":"TERMINAL SANTA FELICIDADE","DIA":"2","NUM":"109121","TABELA":"3","ADAPT":"RAMPA ELÉTRICA","COD":"307"},{"HORA":"10:16","PONTO":"TUBO TIRADENTES","DIA":"2","NUM":"109053","TABELA":"3","ADAPT":"RAMPA ELÉTRICA","COD":"307"},{"HORA":"10:45","PONTO":"TERMINAL BAIRRO ALTO","DIA":"2","NUM":"109120","TABELA":"3","ADAPT":"RAMPA ELÉTRICA","COD":"307"},{"HORA":"11:14","PONTO":"TUBO NESTOR DE CASTRO","DIA":"2","NUM":"109055","TABELA":"3","ADAPT":"RAMPA ELÉTRICA","COD":"307"},{"HORA":"11:35","PONTO":"TERMINAL SANTA FELICIDADE","DIA":"2","NUM":"109121","TABELA":"3","ADAPT":"RAMPA ELÉTRICA","COD":"307"},{"HORA":"11:58","PONTO":"TUBO TIRADENTES","DIA":"2","NUM":"109053","TABELA":"3","ADAPT":"RAMPA ELÉTRICA","COD":"307"},{"HORA":"12:27","PONTO":"TERMINAL BAIRRO ALTO","DIA":"2","NUM":"109120","TABELA":"3","ADAPT":"RAMPA ELÉTRICA","COD":"307"},{"HORA":"12:59","PONTO":"TUBO NESTOR DE CASTRO","DIA":"2","NUM":"109055","TABELA":"3","ADAPT":"RAMPA ELÉTRICA","COD":"307"},{"HORA":"13:22","PONTO":"TERMINAL SANTA FELICIDADE","DIA":"2","NUM":"109121","TABELA":"3","ADAPT":"RAMPA ELÉTRICA","COD":"307"},{"HORA":"13:45","PONTO":"TUBO TIRADENTES","DIA":"2","NUM":"109053","TABELA":"3","ADAPT":"RAMPA ELÉTRICA","COD":"307"},{"HORA":"14:16","PONTO":"TERMINAL BAIRRO ALTO","DIA":"2","NUM":"109120","TABELA":"3","ADAPT":"RAMPA ELÉTRICA","COD":"307"},{"HORA":"14:47","PONTO":"TUBO NESTOR DE CASTRO","DIA":"2","NUM":"109055","TABELA":"3","ADAPT":"RAMPA ELÉTRICA","COD":"307"},{"HORA":"15:10","PONTO":"TERMINAL SANTA FELICIDADE","DIA":"2","NUM":"109121","TABELA":"3","ADAPT":"RAMPA ELÉTRICA","COD":"307"},{"HORA":"15:32","PONTO":"TUBO TIRADENTES","DIA":"2","NUM":"109053","TABELA":"3","ADAPT":"RAMPA ELÉTRICA","COD":"307"},{"HORA":"15:58","PONTO":"TERMINAL BAIRRO ALTO","DIA":"2","NUM":"109120","TABELA":"3","ADAPT":"RAMPA ELÉTRICA","COD":"307"},{"HORA":"16:28","PONTO":"TUBO NESTOR DE CASTRO","DIA":"2","NUM":"109055","TABELA":"3","ADAPT":"RAMPA ELÉTRICA","COD":"307"},{"HORA":"16:51","PONTO":"TERMINAL SANTA FELICIDADE","DIA":"2","NUM":"109121","TABELA":"3","ADAPT":"RAMPA ELÉTRICA","COD":"307"},{"HORA":"17:14","PONTO":"TUBO TIRADENTES","DIA":"2","NUM":"109053","TABELA":"3","ADAPT":"RAMPA ELÉTRICA","COD":"307"},{"HORA":"17:44","PONTO":"TERMINAL BAIRRO ALTO","DIA":"2","NUM":"109120","TABELA":"3","ADAPT":"RAMPA ELÉTRICA","COD":"307"},{"HORA":"18:14","PONTO":"TUBO NESTOR DE CASTRO","DIA":"2","NUM":"109055","TABELA":"3","ADAPT":"RAMPA ELÉTRICA","COD":"307"},{"HORA":"18:37","PONTO":"TERMINAL SANTA FELICIDADE","DIA":"2","NUM":"109121","TABELA":"3","ADAPT":"RAMPA ELÉTRICA","COD":"307"},{"HORA":"18:59","PONTO":"TUBO TIRADENTES","DIA":"2","NUM":"109053","TABELA":"3","ADAPT":"RAMPA ELÉTRICA","COD":"307"},{"HORA":"19:31","PONTO":"TERMINAL BAIRRO ALTO","DIA":"2","NUM":"109120","TABELA":"3","ADAPT":"RAMPA ELÉTRICA","COD":"307"},{"HORA":"20:02","PONTO":"TUBO NESTOR DE CASTRO","DIA":"2","NUM":"109055","TABELA":"3","ADAPT":"RAMPA ELÉTRICA","COD":"307"},{"HORA":"20:24","PONTO":"TERMINAL SANTA FELICIDADE","DIA":"2","NUM":"109121","TABELA":"3","ADAPT":"RAMPA ELÉTRICA","COD":"307"},{"HORA":"20:46","PONTO":"TUBO TIRADENTES","DIA":"2","NUM":"109053","TABELA":"3","ADAPT":"RAMPA ELÉTRICA","COD":"307"}]